netbox_sitemap/__init__.py
netbox_sitemap/filtersets.py
netbox_sitemap/forms.py
netbox_sitemap/models.py
netbox_sitemap/navigation.py
netbox_sitemap/tables.py
netbox_sitemap/urls.py
netbox_sitemap/views.py
netbox_sitemap/widgets.py
netbox_sitemap/api/__init__.py
netbox_sitemap/api/serializers.py
netbox_sitemap/api/urls.py
netbox_sitemap/api/views.py
netbox_sitemap/migrations/0001_initial.py
netbox_sitemap/migrations/0002_sitemap_regions.py
netbox_sitemap/migrations/__init__.py
netbox_sitemap/static/netbox_sitemap/app.js
netbox_sitemap/static/netbox_sitemap/styles.css
netbox_sitemap/static/netbox_sitemap/images/marker.png
netbox_sitemap/static/netbox_sitemap/styles/dark.json
netbox_sitemap/static/netbox_sitemap/styles/liberty.json
netbox_sitemap/templates/netbox_sitemap/sitemap.html
netbox_sitemap/templates/netbox_sitemap/sitemapmap.html
netbox_sitemap/templates/netbox_sitemap/sitemapwidget.html
netbox_sitemap-0.3.0.dist-info/licenses/LICENSE
netbox_sitemap-0.3.0.dist-info/METADATA
netbox_sitemap-0.3.0.dist-info/WHEEL
netbox_sitemap-0.3.0.dist-info/top_level.txt
netbox_sitemap-0.3.0.dist-info/RECORD
